{
  "start_symbol": "Root",
  "actions": {
    "0": {
      "int_literal": {
        "type": "shift",
        "target": 3
      }
    },
    "1": {
      "EOF": {
        "type": "accept"
      }
    },
    "10": {
      "int_literal": {
        "type": "shift",
        "target": 3
      }
    },
    "11": {
      "int_literal": {
        "type": "shift",
        "target": 3
      }
    },
    "12": {
      "int_literal": {
        "type": "shift",
        "target": 3
      }
    },
    "13": {
      "EOF": {
        "type": "reduce",
        "target": 8
      },
      "divide": {
        "type": "reduce",
        "target": 8
      },
      "minus": {
        "type": "reduce",
        "target": 8
      },
      "modulo": {
        "type": "reduce",
        "target": 8
      },
      "plus": {
        "type": "reduce",
        "target": 8
      },
      "times": {
        "type": "reduce",
        "target": 8
      }
    },
    "14": {
      "EOF": {
        "type": "reduce",
        "target": 7
      },
      "divide": {
        "type": "reduce",
        "target": 7
      },
      "minus": {
        "type": "reduce",
        "target": 7
      },
      "modulo": {
        "type": "reduce",
        "target": 7
      },
      "plus": {
        "type": "reduce",
        "target": 7
      },
      "times": {
        "type": "reduce",
        "target": 7
      }
    },
    "15": {
      "EOF": {
        "type": "reduce",
        "target": 9
      },
      "divide": {
        "type": "reduce",
        "target": 9
      },
      "minus": {
        "type": "reduce",
        "target": 9
      },
      "modulo": {
        "type": "reduce",
        "target": 9
      },
      "plus": {
        "type": "reduce",
        "target": 9
      },
      "times": {
        "type": "reduce",
        "target": 9
      }
    },
    "16": {
      "EOF": {
        "type": "reduce",
        "target": 4
      },
      "divide": {
        "type": "shift",
        "target": 8
      },
      "minus": {
        "type": "reduce",
        "target": 4
      },
      "modulo": {
        "type": "shift",
        "target": 10
      },
      "plus": {
        "type": "reduce",
        "target": 4
      },
      "times": {
        "type": "shift",
        "target": 9
      }
    },
    "17": {
      "EOF": {
        "type": "reduce",
        "target": 5
      },
      "divide": {
        "type": "shift",
        "target": 8
      },
      "minus": {
        "type": "reduce",
        "target": 5
      },
      "modulo": {
        "type": "shift",
        "target": 10
      },
      "plus": {
        "type": "reduce",
        "target": 5
      },
      "times": {
        "type": "shift",
        "target": 9
      }
    },
    "2": {
      "EOF": {
        "type": "reduce",
        "target": 6
      },
      "divide": {
        "type": "shift",
        "target": 8
      },
      "minus": {
        "type": "reduce",
        "target": 6
      },
      "modulo": {
        "type": "shift",
        "target": 10
      },
      "plus": {
        "type": "reduce",
        "target": 6
      },
      "times": {
        "type": "shift",
        "target": 9
      }
    },
    "3": {
      "EOF": {
        "type": "reduce",
        "target": 11
      },
      "divide": {
        "type": "reduce",
        "target": 11
      },
      "minus": {
        "type": "reduce",
        "target": 11
      },
      "modulo": {
        "type": "reduce",
        "target": 11
      },
      "plus": {
        "type": "reduce",
        "target": 11
      },
      "times": {
        "type": "reduce",
        "target": 11
      }
    },
    "4": {
      "EOF": {
        "type": "reduce",
        "target": 10
      },
      "divide": {
        "type": "reduce",
        "target": 10
      },
      "minus": {
        "type": "reduce",
        "target": 10
      },
      "modulo": {
        "type": "reduce",
        "target": 10
      },
      "plus": {
        "type": "reduce",
        "target": 10
      },
      "times": {
        "type": "reduce",
        "target": 10
      }
    },
    "5": {
      "EOF": {
        "type": "reduce",
        "target": 1
      }
    },
    "6": {
      "EOF": {
        "type": "reduce",
        "target": 2
      }
    },
    "7": {
      "EOF": {
        "type": "reduce",
        "target": 3
      },
      "minus": {
        "type": "shift",
        "target": 12
      },
      "plus": {
        "type": "shift",
        "target": 11
      }
    },
    "8": {
      "int_literal": {
        "type": "shift",
        "target": 3
      }
    },
    "9": {
      "int_literal": {
        "type": "shift",
        "target": 3
      }
    }
  },
  "gotos": {
    "0": {
      "AddSubTerm": 7,
      "MulDivTerm": 2,
      "PrecedenceChainStart": 6,
      "RHSValue": 4,
      "Root": 1,
      "Rvalue": 5
    },
    "10": {
      "RHSValue": 15
    },
    "11": {
      "MulDivTerm": 16,
      "RHSValue": 4
    },
    "12": {
      "MulDivTerm": 17,
      "RHSValue": 4
    },
    "8": {
      "RHSValue": 13
    },
    "9": {
      "RHSValue": 14
    }
  },
  "productions": [
    {
      "lhs": "__pgpg_start_1",
      "rhs": [
        {
          "name": "Root",
          "terminal": false
        }
      ]
    },
    {
      "lhs": "Root",
      "rhs": [
        {
          "name": "Rvalue",
          "terminal": false
        }
      ]
    },
    {
      "lhs": "Rvalue",
      "rhs": [
        {
          "name": "PrecedenceChainStart",
          "terminal": false
        }
      ]
    },
    {
      "lhs": "PrecedenceChainStart",
      "rhs": [
        {
          "name": "AddSubTerm",
          "terminal": false
        }
      ]
    },
    {
      "lhs": "AddSubTerm",
      "rhs": [
        {
          "name": "AddSubTerm",
          "terminal": false
        },
        {
          "name": "plus",
          "terminal": true
        },
        {
          "name": "MulDivTerm",
          "terminal": false
        }
      ]
    },
    {
      "lhs": "AddSubTerm",
      "rhs": [
        {
          "name": "AddSubTerm",
          "terminal": false
        },
        {
          "name": "minus",
          "terminal": true
        },
        {
          "name": "MulDivTerm",
          "terminal": false
        }
      ]
    },
    {
      "lhs": "AddSubTerm",
      "rhs": [
        {
          "name": "MulDivTerm",
          "terminal": false
        }
      ]
    },
    {
      "lhs": "MulDivTerm",
      "rhs": [
        {
          "name": "MulDivTerm",
          "terminal": false
        },
        {
          "name": "times",
          "terminal": true
        },
        {
          "name": "RHSValue",
          "terminal": false
        }
      ]
    },
    {
      "lhs": "MulDivTerm",
      "rhs": [
        {
          "name": "MulDivTerm",
          "terminal": false
        },
        {
          "name": "divide",
          "terminal": true
        },
        {
          "name": "RHSValue",
          "terminal": false
        }
      ]
    },
    {
      "lhs": "MulDivTerm",
      "rhs": [
        {
          "name": "MulDivTerm",
          "terminal": false
        },
        {
          "name": "modulo",
          "terminal": true
        },
        {
          "name": "RHSValue",
          "terminal": false
        }
      ]
    },
    {
      "lhs": "MulDivTerm",
      "rhs": [
        {
          "name": "RHSValue",
          "terminal": false
        }
      ]
    },
    {
      "lhs": "RHSValue",
      "rhs": [
        {
          "name": "int_literal",
          "terminal": true
        }
      ]
    }
  ]
}